zitncov/__init__.py
zitncov/__main__.py
zitncov/main.py
zitncov/tool.py
zitncov/user.py
zitncov-0.0.2.dist-info/LICENSE
zitncov-0.0.2.dist-info/METADATA
zitncov-0.0.2.dist-info/WHEEL
zitncov-0.0.2.dist-info/entry_points.txt
zitncov-0.0.2.dist-info/top_level.txt
zitncov-0.0.2.dist-info/RECORD
