Metadata-Version: 2.1
Name: zitncov
Version: 0.0.2
Summary: A small function to obtain the health reporting and submission information of Zhengzhou Institute of science and technology.
Home-page: https://github.com/WildboarG/zit-Cov
Author: WildboarG
Author-email: mm62633482@gmail.com
License: MIT
Keywords: zit,ncov
Platform: UNKNOWN
Requires-Python: >=3.6
License-File: LICENSE
Requires-Dist: requests
Requires-Dist: fuckzk
Requires-Dist: argparse
Requires-Dist: rich
